scorecardbundle/__init__.py
scorecardbundle/feature_discretization/ChiMerge.py
scorecardbundle/feature_discretization/FeatureIntervalAdjustment.py
scorecardbundle/feature_discretization/__init__.py
scorecardbundle/feature_encoding/WOE.py
scorecardbundle/feature_encoding/__init__.py
scorecardbundle/feature_selection/FeatureSelection.py
scorecardbundle/feature_selection/__init__.py
scorecardbundle/model_evaluation/ModelEvaluation.py
scorecardbundle/model_evaluation/__init__.py
scorecardbundle/model_interpretation/ScorecardExplainer.py
scorecardbundle/model_interpretation/__init__.py
scorecardbundle/model_score_binning/__init__.py
scorecardbundle/model_training/LogisticRegressionScoreCard.py
scorecardbundle/model_training/__init__.py
scorecardbundle/model_tuning/__init__.py
scorecardbundle/utils/__init__.py
scorecardbundle/utils/func_numpy.py
scorecardbundle-1.2.2.dist-info/LICENSE.txt
scorecardbundle-1.2.2.dist-info/METADATA
scorecardbundle-1.2.2.dist-info/WHEEL
scorecardbundle-1.2.2.dist-info/top_level.txt
scorecardbundle-1.2.2.dist-info/RECORD
