Metadata-Version: 2.1
Name: scorecardbundle
Version: 1.2.2
Summary: The python scorecard modeling library
Home-page: https://github.com/Lantianzz/Scorecard-Bundle
Author: Lantian ZHANG
Author-email: blue.zhanglt@outlook.com
License: UNKNOWN
Keywords: Python Scorecard Modeling
Platform: UNKNOWN
Classifier: Development Status :: 4 - Beta
Classifier: Intended Audience :: Financial and Insurance Industry
Classifier: Topic :: Scientific/Engineering :: Artificial Intelligence
Classifier: License :: OSI Approved :: BSD License
Classifier: Programming Language :: Python :: 3
Requires-Python: >=3.7
License-File: LICENSE.txt
Requires-Dist: numpy
Requires-Dist: scipy
Requires-Dist: pandas
Requires-Dist: matplotlib
Requires-Dist: scikit-learn
